CHANGELOG.md
singer_encodings/__init__.py
singer_encodings/compression.py
singer_encodings/csv.py
singer_encodings/csv_helper.py
singer_encodings/json_schema.py
realit_singer_encodings-2.1.1.dist-info/LICENSE
realit_singer_encodings-2.1.1.dist-info/METADATA
realit_singer_encodings-2.1.1.dist-info/WHEEL
realit_singer_encodings-2.1.1.dist-info/entry_points.txt
realit_singer_encodings-2.1.1.dist-info/RECORD
