Metadata-Version: 2.1
Name: realit-singer-encodings
Version: 2.1.1
Summary: Singer.io encodings library - PipelineWise and Meltano compatible
Home-page: https://github.com/s7clarke10/realit-singer-encodings
License: Apache 2.0
Keywords: singer,meltano,pipelinewise,framework
Requires-Python: >=3.8,<3.13
Classifier: Development Status :: 5 - Production/Stable
Classifier: License :: OSI Approved :: Apache Software License
Classifier: License :: Other/Proprietary License
Classifier: Programming Language :: Python :: 3
Classifier: Programming Language :: Python :: 3.8
Classifier: Programming Language :: Python :: 3.9
Classifier: Programming Language :: Python :: 3.10
Classifier: Programming Language :: Python :: 3.11
Classifier: Programming Language :: Python :: 3.12
Classifier: Topic :: Database
Requires-Dist: realit_singer_python (>=5.0.0,<6.0.0)
Project-URL: Repository, https://github.com/s7clarke10/realit-singer-encodings
